LICENSE
MANIFEST.in
README.md
setup.py
keras_quadopt/__init__.py
keras_quadopt/problem.py
keras_quadopt/utils.py
keras_quadopt.egg-info/PKG-INFO
keras_quadopt.egg-info/SOURCES.txt
keras_quadopt.egg-info/dependency_links.txt
keras_quadopt.egg-info/requires.txt
keras_quadopt.egg-info/top_level.txt
keras_quadopt.egg-info/zip-safe
test/__init__.py
test/test_aggregate_matrices.py
test/test_get_weights.py