Metadata-Version: 2.1
Name: keras-quadopt
Version: 0.2.0
Summary: Solving quadratic optimization problems with Keras.
Home-page: http://github.com/ulf1/keras-quadopt
Author: Ulf Hamster
Author-email: 554c46@gmail.com
License: Apache License 2.0
Platform: UNKNOWN
Requires-Python: >=3.7
License-File: LICENSE
